{
  "info": {
    "key": "b35011_0415"
  },
  "sheets": {
    "מזומנים": {
      "columns": [
        "שם המנפיק/שם נייר ערך",
        "מספר ני\"ע",
        "מספר מנפיק",
        "דירוג",
        "שם מדרג",
        "סוג מטבע",
        "שיעור ריבית",
        "תשואה לפידיון",
        "שווי שוק",
        "שעור מנכסי אפיק ההשקעה",
        "שעור מסך נכסי השקעה"
      ],
      "data": [
        [
          "עו'ש- בנק מזרחי",
          "1111111111- 20- בנק מזרחי",
          20,
          "AAA",
          "מעלות",
          "שקל חדש",
          0,
          0,
          2569.68339,
          97.23,
          3.88
        ],
        [
          "לי\"ש- בנק מזרחי",
          "70002- 20- בנק מזרחי",
          20,
          "AAA",
          "מעלות",
          "לירה שטרלינג",
          0,
          0,
          27.07715976,
          1.02,
          0.04
        ],
        [
          "דולר- בנק מזרחי",
          "20001- 20- בנק מזרחי",
          20,
          "AAA",
          "מעלות",
          "דולר אמריקאי",
          0,
          0,
          46.08999478,
          1.74,
          0.07
        ]
      ]
    },
    "אג\"ח קונצרני": {
      "columns": [
        "שם המנפיק/שם נייר ערך",
        "מספר ני\"ע",
        "זירת מסחר",
        "ספק מידע",
        "מספר מנפיק",
        "ענף מסחר",
        "דירוג",
        "שם מדרג",
        "תאריך רכישה",
        "מח\"מ",
        "סוג מטבע",
        "שיעור ריבית",
        "תשואה לפידיון",
        "ערך נקוב",
        "שער",
        "שווי שוק",
        "שעור מערך נקוב מונפק",
        "שעור מנכסי אפיק ההשקעה",
        "שעור מסך נכסי השקעה"
      ],
      "data": [
        [
          "אדמה אגח  2- אדמה בע\"מ",
          1110915,
          "TASE",
          "אחר",
          1063,
          "כימיה, גומי ופלסטיק",
          "AA-",
          "מעלות",
          "07/01/13",
          9.27,
          "שקל חדש",
          5.15,
          5.13,
          132743.0,
          121.31,
          161.0305333,
          0.001,
          1.96,
          0.24
        ],
        [
          "אמות אגח 1- אמות השקעות",
          1097385,
          "TASE",
          "אחר",
          1328,
          "נדל\"ן ובינוי",
          "AA-",
          "מעלות",
          "26/11/08",
          1.94,
          "שקל חדש",
          4.95,
          1.26,
          135593.21,
          128.96,
          174.861003616,
          0.03,
          2.13,
          0.26
        ],
        [
          "גזית גלוב אג11- גזית גלוב",
          1260546,
          "TASE",
          "אחר",
          126,
          "נדל\"ן ובינוי",
          "AA-",
          "מעלות",
          "13/12/12",
          5.8,
          "שקל חדש",
          5.35,
          3.3,
          63426.0,
          119.02,
          75.4896252,
          0.001,
          0.92,
          0.11
        ],
        [
          "דיסקונט מנפיקים א- דיסקונט",
          7480015,
          "TASE",
          "אחר",
          691,
          "בנקים",
          "AA-",
          "מעלות",
          "26/11/08",
          1.21,
          "שקל חדש",
          5.5,
          1.03,
          67414.96,
          135.82,
          91.562998672,
          0.03,
          1.11,
          0.14
        ],
        [
          "מליסרון   אגח ו- מליסרון",
          3230125,
          "TASE",
          "אחר",
          323,
          "נדל\"ן ובינוי",
          "AA-",
          "מעלות",
          "29/01/12",
          4.08,
          "שקל חדש",
          4.9,
          1.79,
          332500.0,
          116.77,
          388.26025,
          0.03,
          4.72,
          0.59
        ],
        [
          "דש איפקס  אגח ג-חסום עד 8/13- מיטב דש",
          1121763,
          "TASE",
          "אחר",
          1064,
          "שירותים פיננסיים",
          "A1",
          "מידרוג",
          "14/02/13",
          5,
          "שקל חדש",
          3.95,
          1.78,
          356315.36,
          117.6,
          419.02686336,
          0.06,
          5.09,
          0.63
        ],
        [
          "נכסים ובנין אגח.6- חברה לנכסים ובנין",
          6990188,
          "TASE",
          "אחר",
          699,
          "נדל\"ן ובינוי",
          "A1",
          "מידרוג",
          "29/12/15",
          4.17,
          "שקל חדש",
          4.95,
          2.5,
          150000.0,
          112.43,
          168.645,
          0.02,
          2.05,
          0.25
        ],
        [
          "סלקום אגח 4- סלקום ישראל בע\"מ",
          1107333,
          "TASE",
          "אחר",
          170,
          "תקשורת ומדיה",
          "A+",
          "מעלות",
          "08/08/12",
          0.98,
          "שקל חדש",
          5.19,
          1.46,
          251808.4,
          123.7,
          311.4869908,
          0.04,
          3.79,
          0.47
        ],
        [
          "מגה אור אג\"ח 4- מגה אור",
          1130632,
          "TASE",
          "אחר",
          1450,
          "נדל\"ן ובינוי",
          "A",
          "מעלות",
          "25/11/15",
          4.51,
          "שקל חדש",
          3.35,
          2.07,
          95000.0,
          105.35,
          100.0825,
          0.02,
          1.22,
          0.15
        ],
        [
          "נכסים ובנין אגח ג- חברה לנכסים ובנין",
          6990139,
          "TASE",
          "אחר",
          699,
          "נדל\"ן ובינוי",
          "A",
          "מעלות",
          "15/08/12",
          1.38,
          "שקל חדש",
          5.0,
          1.17,
          213521.75,
          126.18,
          269.42174415,
          0.04,
          3.27,
          0.41
        ],
        [
          "שלמה הח אג14- שלמה החזקות",
          1410265,
          "TASE",
          "אחר",
          2770,
          "שירותים",
          "A",
          "מעלות",
          "19/01/15",
          2.08,
          "שקל חדש",
          3.75,
          1.95,
          220134.72,
          104.67,
          230.415011424,
          0.03,
          2.8,
          0.35
        ],
        [
          "שלמה החזקות אגח 11- שלמה החזקות",
          1410224,
          "TASE",
          "אחר",
          2770,
          "שירותים",
          "A",
          "מעלות",
          "16/02/12",
          1.11,
          "שקל חדש",
          2.3,
          1.77,
          168490.56,
          105.45,
          177.67329552,
          0.06,
          2.16,
          0.27
        ],
        [
          "בזן       אגח ז- בתי זיקוק לנפט",
          2590438,
          "TASE",
          "אחר",
          259,
          "כימיה, גומי ופלסטיק",
          "BBB+",
          "מעלות",
          "30/12/15",
          2.11,
          "שקל חדש",
          5.69,
          0.0,
          111379.17,
          128.83,
          143.489784711,
          0.001,
          1.74,
          0.22
        ],
        [
          "מבני תעשיה אגח 14- מבני תעשיה",
          2260412,
          "TASE",
          "אחר",
          226,
          "נדל\"ן ובינוי",
          "BBB+",
          "מעלות",
          "30/12/13",
          2.24,
          "שקל חדש",
          6.6,
          4.97,
          725554.0,
          104.97,
          761.6140338,
          0.05,
          9.26,
          1.15
        ],
        [
          "דיסקונט הש אג6- דיסקונט השקעות",
          6390207,
          "TASE",
          "אחר",
          639,
          "השקעות ואחזקות",
          "BBB-",
          "מעלות",
          "01/02/12",
          4.83,
          "שקל חדש",
          4.95,
          10.58,
          90000.0,
          90.5,
          81.45,
          0.001,
          0.99,
          0.12
        ],
        [
          "דיסקונט השק אגח 4- דיסקונט השקעות",
          6390157,
          "TASE",
          "אחר",
          639,
          "השקעות ואחזקות",
          "BBB-",
          "מעלות",
          "01/02/12",
          0.3,
          "שקל חדש",
          5.0,
          5.23,
          42973.81,
          126.97,
          54.563846557,
          0.03,
          0.66,
          0.08
        ],
        [
          "אידיבי פיתוח אגח 7- אי די בי חברה לפיתוח",
          7980121,
          "TASE",
          "אחר",
          798,
          "השקעות ואחזקות",
          "B",
          "מעלות",
          "23/04/12",
          1.27,
          "שקל חדש",
          4.5,
          17.33,
          503734.96,
          98.45,
          495.92706812,
          0.06,
          6.03,
          0.75
        ],
        [
          "גליל מור אגח א- גליל מור",
          1108877,
          "TASE",
          "אחר",
          1505,
          "אג\"ח מובנות",
          "Caa1",
          "מידרוג",
          "22/06/10",
          1.42,
          "שקל חדש",
          3.9,
          9.26,
          190604.56,
          107.29,
          204.499632424,
          0.18,
          2.49,
          0.31
        ],
        [
          "מגדל הון  אגח ד- מגדל ביטוח",
          1137033,
          "TASE",
          "אחר",
          1597,
          "ביטוח",
          "Aa1",
          "מידרוג",
          "15/12/15",
          6.55,
          "שקל חדש",
          3.39,
          3.34,
          330000.0,
          100.9,
          332.97,
          0.001,
          4.05,
          0.5
        ],
        [
          "תעשיה אוירית אג4- תעשיה אוירית",
          1133131,
          "TASE",
          "אחר",
          2160,
          "ביטחוניות",
          "AA",
          "מעלות",
          "04/08/14",
          6.68,
          "שקל חדש",
          1.05,
          1.09,
          390000.0,
          99.79,
          389.181,
          0.08,
          4.73,
          0.59
        ],
        [
          "קרסו אגח א- קרסו",
          1136464,
          "TASE",
          "אחר",
          4210,
          "מסחר",
          "Aa3",
          "מידרוג",
          "17/09/15",
          4.96,
          "שקל חדש",
          2.75,
          2.42,
          80000.0,
          103.06,
          82.448,
          0.03,
          1.0,
          0.12
        ],
        [
          "בי קומיוניקשנס אג\"ח 2- בי קומיוניקיישנס",
          1120872,
          "TASE",
          "אחר",
          1422,
          "תקשורת ומדיה",
          "A1",
          "מידרוג",
          "11/02/14",
          1.68,
          "שקל חדש",
          6.5,
          1.6,
          381640.0,
          110.36,
          421.177904,
          0.05,
          5.12,
          0.64
        ],
        [
          "נכסים ובנין אגח 7- חברה לנכסים ובנין",
          6990196,
          "TASE",
          "אחר",
          699,
          "נדל\"ן ובינוי",
          "A1",
          "מידרוג",
          "27/05/15",
          4.71,
          "שקל חדש",
          7.05,
          3.65,
          108000.0,
          118.4,
          127.872,
          0.02,
          1.55,
          0.19
        ],
        [
          "אשטרום קב אגח ב- קבוצת אשטרום",
          1132331,
          "TASE",
          "אחר",
          4660,
          "נדל\"ן ובינוי",
          "A",
          "מעלות",
          "28/07/15",
          4.32,
          "שקל חדש",
          4.2,
          4.06,
          211450.0,
          102.8,
          217.3706,
          0.02,
          2.64,
          0.33
        ],
        [
          "דלק קבוצה אג31- דלק קבוצה",
          1134790,
          "TASE",
          "אחר",
          1095,
          "השקעות ואחזקות",
          "A",
          "מעלות",
          "15/10/15",
          6.24,
          "שקל חדש",
          4.3,
          4.64,
          200000.0,
          101.05,
          202.1,
          0.01,
          2.46,
          0.3
        ],
        [
          "קרדן רכב  אגח ח- קרדן רכב",
          4590147,
          "TASE",
          "אחר",
          4685,
          "שירותים",
          "A",
          "מעלות",
          "16/02/15",
          3.58,
          "שקל חדש",
          3.4,
          2.91,
          273529.38,
          103.34,
          282.665261292,
          0.1,
          3.44,
          0.43
        ],
        [
          "אשדר      אגח ד- אשדר חברה לבניה",
          1135607,
          "TASE",
          "אחר",
          1448,
          "נדל\"ן ובינוי",
          "A3",
          "מידרוג",
          "11/05/15",
          4.5,
          "שקל חדש",
          4.2,
          4.27,
          173000.0,
          101.13,
          174.9549,
          0.14,
          2.13,
          0.26
        ],
        [
          "דור אלון  אגח ה- דור אלון",
          1136761,
          "TASE",
          "אחר",
          1072,
          "שירותים",
          "A3",
          "מידרוג",
          "05/11/15",
          4.06,
          "שקל חדש",
          4.55,
          3.94,
          200000.0,
          104.5,
          209.0,
          0.08,
          2.54,
          0.32
        ],
        [
          "חשמל     אגח 26- מנרב",
          6000202,
          "TASE",
          "אחר",
          155,
          "שירותים",
          "A3",
          "מידרוג",
          "09/06/15",
          5.49,
          "שקל חדש",
          4.8,
          2.08,
          295500.0,
          117.15,
          346.17825,
          0.07,
          4.21,
          0.52
        ],
        [
          "אלדן תחבורה אגח א'- אלדן תחבורה",
          1134840,
          "TASE",
          "אחר",
          1636,
          "שירותים",
          "Baa1",
          "מידרוג",
          "02/03/15",
          2.49,
          "שקל חדש",
          4.3,
          4.15,
          250000.0,
          102.13,
          255.325,
          0.04,
          3.1,
          0.39
        ],
        [
          "חלל תקשורת  אגח יג- חלל",
          1136555,
          "TASE",
          "אחר",
          1132,
          "תקשורת ומדיה",
          0,
          "לא מדורג",
          "15/10/15",
          5.23,
          "שקל חדש",
          5.5,
          6.42,
          350000.0,
          97.09,
          339.815,
          0.06,
          4.13,
          0.51
        ],
        [
          "פורמולה אג\"ח ב- פורמולה",
          2560159,
          "TASE",
          "אחר",
          2345,
          "שירותי מידע",
          "A+",
          "מעלות",
          "17/09/15",
          3.23,
          "שקל חדש",
          2.74,
          0.0,
          130000.0,
          101.4,
          131.82,
          0.1,
          1.6,
          0.2
        ],
        [
          "BCOM7 7.3 02/21- בי קומיוניקיישנס",
          183707,
          "NYSE",
          "בלומברג",
          1422,
          "Telecommunication Services",
          "BB-",
          "S&P",
          "25/11/14",
          "",
          "דולר אמריקאי",
          7.38,
          0.0,
          96000.0,
          108.28536989583333,
          405.6283328002,
          0.001,
          4.93,
          0.61
        ]
      ]
    },
    "מניות": {
      "columns": [
        "שם המנפיק/שם נייר ערך",
        "מספר ני\"ע",
        "זירת מסחר",
        "ספק מידע",
        "מספר מנפיק",
        "ענף מסחר",
        "סוג מטבע",
        "ערך נקוב",
        "שער",
        "שווי שוק",
        "שעור מערך נקוב מונפק",
        "שעור מנכסי אפיק ההשקעה",
        "שעור מסך נכסי השקעה"
      ],
      "data": [
        [
          "אלביט מערכות- אלביט מערכות",
          1081124,
          "TASE",
          "אחר",
          1040,
          "ביטחוניות",
          "שקל חדש",
          439,
          34280.0,
          150.4892,
          0.001,
          3.7,
          0.23
        ],
        [
          "דיסקונט- דיסקונט",
          691212,
          "TASE",
          "אחר",
          691,
          "בנקים",
          "שקל חדש",
          17407,
          706.0,
          122.89342,
          0.001,
          3.02,
          0.19
        ],
        [
          "לאומי- לאומי",
          604611,
          "TASE",
          "אחר",
          604,
          "בנקים",
          "שקל חדש",
          11178,
          1350.0,
          150.903,
          0.001,
          3.71,
          0.23
        ],
        [
          "אפקו- אופקו",
          1129543,
          "TASE",
          "אחר",
          1610,
          "השקעות במדעי החיים",
          "שקל חדש",
          1150,
          3955.0,
          45.4825,
          0.001,
          1.12,
          0.07
        ],
        [
          "דלק קבוצה- דלק קבוצה",
          1084128,
          "TASE",
          "אחר",
          1095,
          "השקעות ואחזקות",
          "שקל חדש",
          121,
          78010.0,
          94.3921,
          0.001,
          2.32,
          0.14
        ],
        [
          "ישרמקו יהש- ישראמקו",
          232017,
          "TASE",
          "אחר",
          232,
          "חיפושי נפט וגז",
          "שקל חדש",
          152565,
          67.2,
          102.52368,
          0.001,
          2.52,
          0.15
        ],
        [
          "שטראוס- שטראוס גרופ בע\"מ",
          746016,
          "TASE",
          "אחר",
          340,
          "מזון",
          "שקל חדש",
          1297,
          5795.0,
          75.16115,
          0.001,
          1.85,
          0.11
        ],
        [
          "טבע- טבע",
          629014,
          "TASE",
          "אחר",
          629,
          "מסחר",
          "שקל חדש",
          475,
          25450.0,
          120.8875,
          0.001,
          2.97,
          0.18
        ],
        [
          "כיל- כיל",
          281014,
          "TASE",
          "אחר",
          281,
          "מסחר",
          "שקל חדש",
          4066,
          1581.0,
          64.28346,
          0.001,
          1.58,
          0.1
        ],
        [
          "גזית גלוב- גזית גלוב",
          126011,
          "TASE",
          "אחר",
          126,
          "נדל\"ן ובינוי",
          "שקל חדש",
          2899,
          3468.0,
          100.53732,
          0.001,
          2.47,
          0.15
        ],
        [
          "עזריאלי קבוצה- עזריאלי קבוצה",
          1119478,
          "TASE",
          "אחר",
          2350,
          "נדל\"ן ובינוי",
          "שקל חדש",
          1347,
          14500.0,
          195.315,
          0.001,
          4.8,
          0.29
        ],
        [
          "נייס- נייס",
          273011,
          "TASE",
          "אחר",
          273,
          "תוכנה ואינטרנט",
          "שקל חדש",
          499,
          22450.0,
          112.0255,
          0.001,
          2.75,
          0.17
        ],
        [
          "מיטרוניקס- מיטרוניקס",
          1091065,
          "TASE",
          "אחר",
          1212,
          "אלקטרוניקה ואופטיקה",
          "שקל חדש",
          16063,
          1008.0,
          161.91504,
          0.02,
          3.98,
          0.24
        ],
        [
          "איידיאיי ביטוח- איי די איי",
          1129501,
          "TASE",
          "אחר",
          1566,
          "ביטוח",
          "שקל חדש",
          2473,
          17700.0,
          437.721,
          0.02,
          10.76,
          0.66
        ],
        [
          "דלק רכב- דלק מערכות רכב",
          829010,
          "TASE",
          "אחר",
          829,
          "מסחר",
          "שקל חדש",
          2038,
          3470.0,
          70.7186,
          0.001,
          1.74,
          0.11
        ],
        [
          "אינרום- אינרום בניה",
          1132356,
          "TASE",
          "אחר",
          1616,
          "מתכת ומוצרי בניה",
          "שקל חדש",
          6561,
          926.0,
          60.75486,
          0.01,
          1.49,
          0.09
        ],
        [
          "אירפורט סיטי- אירפורט סיטי",
          1095835,
          "TASE",
          "אחר",
          1300,
          "נדל\"ן ובינוי",
          "שקל חדש",
          1850,
          3499.0,
          64.7315,
          0.001,
          1.59,
          0.1
        ],
        [
          "אלוני חץ- אלוני חץ",
          390013,
          "TASE",
          "אחר",
          390,
          "נדל\"ן ובינוי",
          "שקל חדש",
          4501,
          2820.0,
          126.9282,
          0.001,
          3.12,
          0.19
        ],
        [
          "בראק אן וי- בראק אן וי",
          1121607,
          "TASE",
          "אחר",
          1560,
          "נדל\"ן ובינוי",
          "שקל חדש",
          591,
          24310.0,
          143.6721,
          0.01,
          3.53,
          0.22
        ],
        [
          "ריט 1- ריט1",
          1098920,
          "TASE",
          "אחר",
          2410,
          "נדל\"ן ובינוי",
          "שקל חדש",
          20760,
          1039.0,
          215.6964,
          0.01,
          5.3,
          0.33
        ],
        [
          "שיכון ובינוי- שיכון ובינוי בע\"מ",
          1081942,
          "TASE",
          "אחר",
          500,
          "נדל\"ן ובינוי",
          "שקל חדש",
          8900,
          614.0,
          54.646,
          0.001,
          1.34,
          0.08
        ],
        [
          "ספנטק- ספנטק",
          1090117,
          "TASE",
          "אחר",
          4105,
          "עץ, נייר ודפוס",
          "שקל חדש",
          9600,
          1426.0,
          136.896,
          0.01,
          3.37,
          0.21
        ],
        [
          "סלקום- סלקום ישראל בע\"מ",
          1101534,
          "TASE",
          "אחר",
          170,
          "תקשורת ומדיה",
          "שקל חדש",
          628,
          2423.0,
          15.21644,
          0.001,
          0.37,
          0.02
        ],
        [
          "ארד- ארד",
          1091651,
          "TASE",
          "אחר",
          1219,
          "אלקטרוניקה ואופטיקה",
          "שקל חדש",
          547,
          3421.0,
          18.71287,
          0.001,
          0.46,
          0.03
        ],
        [
          "סקופ- סקופ מתכות בע\"מ",
          288019,
          "TASE",
          "אחר",
          430,
          "מסחר",
          "שקל חדש",
          1900,
          4800.0,
          91.2,
          0.02,
          2.24,
          0.14
        ],
        [
          "רבל- רבל",
          1103878,
          "TASE",
          "אחר",
          4285,
          "מסחר",
          "שקל חדש",
          1607,
          744.3,
          11.960901,
          0.001,
          0.29,
          0.02
        ],
        [
          "רם און- רם און",
          1090943,
          "TASE",
          "אחר",
          4679,
          "מסחר",
          "שקל חדש",
          3479,
          1919.0,
          66.76201,
          0.02,
          1.64,
          0.1
        ],
        [
          "חמת- חמת",
          384016,
          "TASE",
          "אחר",
          384,
          "מתכת ומוצרי בניה",
          "שקל חדש",
          6044,
          1029.0,
          62.19276,
          0.02,
          1.53,
          0.09
        ],
        [
          "מישורים- מישורים",
          1105196,
          "TASE",
          "אחר",
          1467,
          "נדל\"ן ובינוי",
          "שקל חדש",
          8800,
          503.6,
          44.3168,
          0.04,
          1.09,
          0.07
        ],
        [
          "סלע נדל\"ן- סלע נדלן",
          1109644,
          "TASE",
          "אחר",
          4110,
          "נדל\"ן ובינוי",
          "שקל חדש",
          14421,
          553.0,
          79.74813,
          0.01,
          1.96,
          0.12
        ],
        [
          "V - VISA INC-CLASS- VISA INC",
          "US92826C8394",
          "NYSE",
          "בלומברג",
          2495,
          "Diversified Financials",
          "דולר אמריקאי",
          840,
          7755.0,
          254.184084,
          0.001,
          6.25,
          0.38
        ],
        [
          "PYPL US- PYPL",
          "US70450Y1038",
          "NASDAQ",
          "בלומברג",
          4673,
          "Software   Services",
          "דולר אמריקאי",
          913,
          3620.0,
          128.9634412,
          0.001,
          3.17,
          0.19
        ],
        [
          "GOOGL - Google A Class- GOOGLE",
          "US38259P5089",
          "NASDAQ",
          "בלומברג",
          960,
          "Technology Hardware   Equipment",
          "דולר אמריקאי",
          91,
          77801.0,
          276.25734682,
          0.001,
          6.79,
          0.42
        ],
        [
          "EASYJET PLC-EZJ- EASY JET PLC",
          "GBOOB7KR2P84",
          "LSE",
          "בלומברג",
          4608,
          "Transportation",
          "לירה שטרלינג",
          2080,
          1740.0,
          209.334528,
          0.001,
          5.15,
          0.32
        ]
      ]
    },
    "תעודות סל": {
      "columns": [
        "שם המנפיק/שם נייר ערך",
        "מספר ני\"ע",
        "זירת מסחר",
        "מספר מנפיק",
        "ענף מסחר",
        "סוג מטבע",
        "ערך נקוב",
        "שער",
        "שווי שוק",
        "שעור מערך נקוב מונפק",
        "שעור מנכסי אפיק ההשקעה",
        "שעור מסך נכסי השקעה"
      ],
      "data": [
        [
          "הראל סל ת\"א 25- הראל הנפקות",
          1113703,
          "TASE",
          1523,
          "תעודות סל",
          "שקל חדש",
          51716,
          1528.0,
          790.22048,
          0.06,
          3.29,
          1.19
        ],
        [
          "פסגות א ת\"א 25- פסגות בית השקעות",
          1125319,
          "TASE",
          1108,
          "תעודות סל",
          "שקל חדש",
          155367,
          1529.0,
          2375.56143,
          0.05,
          9.89,
          3.58
        ],
        [
          "פסגות סל ת\"א 100- פסגות בית השקעות",
          1096593,
          "TASE",
          1108,
          "תעודות סל",
          "שקל חדש",
          133753,
          1316.0,
          1760.18948,
          0.09,
          7.33,
          2.65
        ],
        [
          "קסם ת\"א 100- קסם תעודות סל",
          1117266,
          "TASE",
          1224,
          "תעודות סל",
          "שקל חדש",
          3899,
          13120.0,
          511.5488,
          0.001,
          2.13,
          0.77
        ],
        [
          "קסם ת\"א 25- קסם תעודות סל",
          1116979,
          "TASE",
          1224,
          "תעודות סל",
          "שקל חדש",
          5255,
          15250.0,
          801.3875,
          0.02,
          3.34,
          1.21
        ],
        [
          "תכלית יתר 50- תכלית בית השקעות",
          1109305,
          "TASE",
          1223,
          "תעודות סל",
          "שקל חדש",
          50000,
          560.5,
          280.25,
          0.01,
          1.17,
          0.42
        ],
        [
          "תכלית תא SMALL MIDCAP- תכלית בית השקעות",
          1129527,
          "TASE",
          1223,
          "תעודות סל",
          "שקל חדש",
          9287,
          10150.0,
          942.6305,
          0.22,
          3.93,
          1.42
        ],
        [
          "הראל סל נאסד\"ק 100- הראל הנפקות",
          1116458,
          "TASE",
          1523,
          "תעודות סל",
          "שקל חדש",
          46805,
          1866.0,
          873.3813,
          0.05,
          3.64,
          1.32
        ],
        [
          "פסגות ארה\"ב בנקים אזוריים שקלי- פסגות בית השקעות",
          1135961,
          "TASE",
          1108,
          "תעודות סל",
          "שקל חדש",
          13101,
          1219.0,
          159.70119,
          0.04,
          0.67,
          0.24
        ],
        [
          "פסגות דאו ג'ונס- פסגות בית השקעות",
          1127950,
          "TASE",
          1108,
          "תעודות סל",
          "שקל חדש",
          6660,
          7215.0,
          480.519,
          0.04,
          2.0,
          0.72
        ],
        [
          "פסגות דיבידנד אירופה- פסגות בית השקעות",
          1099522,
          "TASE",
          1108,
          "תעודות סל",
          "שקל חדש",
          3015,
          7300.0,
          220.095,
          0.09,
          0.92,
          0.33
        ],
        [
          "פסגות סל שקלי S P 500- פסגות בית השקעות",
          1116060,
          "TASE",
          1108,
          "תעודות סל",
          "שקל חדש",
          4050,
          22880.0,
          926.64,
          0.06,
          3.86,
          1.4
        ],
        [
          "קסם Eero Stoxx Health- קסם תעודות סל",
          1130756,
          "TASE",
          1224,
          "תעודות סל",
          "שקל חדש",
          671,
          34280.0,
          230.0188,
          0.04,
          0.96,
          0.35
        ],
        [
          "קסם אוסטרליה- קסם תעודות סל",
          1107754,
          "TASE",
          1224,
          "תעודות סל",
          "שקל חדש",
          7400,
          1455.0,
          107.67,
          0.03,
          0.45,
          0.16
        ],
        [
          "קסם גרמניה MID CAP מנוטרלת מטב- קסם תעודות סל",
          1130731,
          "TASE",
          1224,
          "תעודות סל",
          "שקל חדש",
          7000,
          2037.0,
          142.59,
          0.01,
          0.59,
          0.22
        ],
        [
          "קסם דאו ג'ונס 30- קסם תעודות סל",
          1117308,
          "TASE",
          1224,
          "תעודות סל",
          "שקל חדש",
          5112,
          6858.0,
          350.58096,
          0.01,
          1.46,
          0.53
        ],
        [
          "קסם דאקס שקלי- קסם תעודות סל",
          1121441,
          "TASE",
          1224,
          "תעודות סל",
          "שקל חדש",
          22240,
          10500.0,
          2335.2,
          0.15,
          9.73,
          3.52
        ],
        [
          "קסם יורוסטוקס 50- קסם תעודות סל",
          1117282,
          "TASE",
          1224,
          "תעודות סל",
          "שקל חדש",
          1600,
          13690.0,
          219.04,
          0.01,
          0.91,
          0.33
        ],
        [
          "קסם נאסד\"ק- קסם תעודות סל",
          1116904,
          "TASE",
          1224,
          "תעודות סל",
          "שקל חדש",
          5331,
          17380.0,
          926.5278,
          0.04,
          3.86,
          1.4
        ],
        [
          "קסם צריכה ארה\"ב -IXY- קסם תעודות סל",
          1130798,
          "TASE",
          1224,
          "תעודות סל",
          "שקל חדש",
          911,
          30660.0,
          279.3126,
          0.04,
          1.16,
          0.42
        ],
        [
          "תכלית - STOXX EUROPE 600- תכלית בית השקעות",
          1129980,
          "TASE",
          1223,
          "תעודות סל",
          "שקל חדש",
          37247,
          1640.0,
          610.8508,
          0.07,
          2.54,
          0.92
        ],
        [
          "תכלית S P 500- תכלית בית השקעות",
          1095710,
          "TASE",
          1223,
          "תעודות סל",
          "שקל חדש",
          15344,
          8532.0,
          1309.15008,
          0.06,
          5.45,
          1.97
        ],
        [
          "תכלית צרפת CA מנוטרלת מטבע- תכלית בית השקעות",
          1135649,
          "TASE",
          1223,
          "תעודות סל",
          "שקל חדש",
          450,
          8700.0,
          39.15,
          0.01,
          0.16,
          0.06
        ],
        [
          "תכלית ראסל 2000- תכלית בית השקעות",
          1127935,
          "TASE",
          1223,
          "תעודות סל",
          "שקל חדש",
          20644,
          4516.0,
          932.28304,
          0.22,
          3.88,
          1.41
        ],
        [
          "XLF - Financial Select- STATE STREET-SPDRS",
          "US81369Y6059",
          "NYSE",
          4640,
          "Banks",
          "דולר אמריקאי",
          3170,
          2383.0,
          294.7613722,
          0.001,
          1.23,
          0.44
        ],
        [
          "XLY - CONSUMER DISCRETIONARY- SSGA FUNDS MANAGEMENT",
          "US81369Y4070",
          "NYSE",
          970,
          "Consumer Durables   Apparel",
          "דולר אמריקאי",
          950,
          7816.08,
          289.73426952,
          0.001,
          1.21,
          0.44
        ],
        [
          "HEALTH CARE XLV- STATE STREET-SPDRS",
          "us81369y2090",
          "NYSE",
          4640,
          "Health Care Equipment   Services",
          "דולר אמריקאי",
          1600,
          7203.0,
          449.697696,
          0.001,
          1.87,
          0.68
        ],
        [
          "DAXEX  GY - DAX- BlackRock Fund Advisors",
          "DE0005933931",
          "FWB",
          2235,
          "Other",
          "אירו",
          1198,
          9497.0,
          483.175678008,
          0.001,
          2.01,
          0.73
        ],
        [
          "ISF LN - FTSE 100- BlackRock Fund Advisors",
          "IE0005042456",
          "LSE",
          2235,
          "Other",
          "לירה שטרלינג",
          17500,
          616.2,
          623.71764,
          0.001,
          2.6,
          0.94
        ],
        [
          "ISHARES MSCI SP EWP US- BlackRock Fund Advisors",
          "US4642867646",
          "NYSE",
          2235,
          "Other",
          "דולר אמריקאי",
          1200,
          2827.0,
          132.371448,
          0.001,
          0.55,
          0.2
        ],
        [
          "QQQQ - Nasdaq 100- INVESCO-POWERSHARES",
          "US73935A1043",
          "NASDAQ",
          4643,
          "Other",
          "דולר אמריקאי",
          3011,
          11186.0,
          1314.23441492,
          0.001,
          5.47,
          1.98
        ],
        [
          "DJ STOXX 600 OP- SOURCE",
          "IE00B5MTWD60",
          "FWB",
          4585,
          "Other",
          "אירו",
          545,
          7239.0,
          167.54708934,
          0.001,
          0.7,
          0.25
        ],
        [
          "SDJ600 GY-EURO STOXX 600- SOURCE",
          "IEOOB6OSWW18",
          "FWB",
          4585,
          "Other",
          "אירו",
          488,
          7039.0,
          145.878938976,
          0.001,
          0.61,
          0.22
        ],
        [
          "SOURCE JPX-NKY- SOURCE",
          "IE00BVGC6751",
          "LSE",
          4585,
          "Other",
          "דולר אמריקאי",
          6160,
          1422.5,
          341.916652,
          0.001,
          1.42,
          0.52
        ],
        [
          "SPXS LN -  S P 500- SOURCE",
          "IE00B3YCGJ38",
          "LSE",
          4585,
          "Other",
          "דולר אמריקאי",
          280,
          35029.0,
          382.7128424,
          0.001,
          1.59,
          0.58
        ],
        [
          "SDY - S P DIVIDEND- STATE STREET-SPDRS",
          "US78464A7634",
          "NYSE",
          4640,
          "Other",
          "דולר אמריקאי",
          1100,
          7357.0,
          315.777154,
          0.001,
          1.32,
          0.48
        ],
        [
          "SPY - S P 500- STATE STREET-SPDRS",
          "US78462F1030",
          "NYSE",
          4640,
          "Other",
          "דולר אמריקאי",
          697,
          20387.0,
          554.46401578,
          0.001,
          2.31,
          0.84
        ],
        [
          "DXJ - WISDOM TREE JAPAN- WISDOM TREE",
          "US97717W8516",
          "NYSE",
          3115,
          "Other",
          "דולר אמריקאי",
          1900,
          5008.0,
          371.283104,
          0.001,
          1.55,
          0.56
        ]
      ]
    },
    "קרנות נאמנות": {
      "columns": [
        "שם המנפיק/שם נייר ערך",
        "מספר ני\"ע",
        "זירת מסחר",
        "מספר מנפיק",
        "ענף מסחר",
        "דירוג",
        "שם מדרג",
        "סוג מטבע",
        "ערך נקוב",
        "שער",
        "שווי שוק",
        "שעור מערך נקוב מונפק",
        "שעור מנכסי אפיק ההשקעה",
        "שעור מסך נכסי השקעה"
      ],
      "data": [
        [
          "ת\"א 25 MTF- מגדל ביטוח",
          5109897,
          "TASE",
          1597,
          "אחר",
          0,
          "לא מדורג",
          "שקל חדש",
          245083.0,
          153.45,
          376.0798635,
          0.001,
          21.3,
          0.57
        ],
        [
          "EDM TRICOLORE FRANCE- ROTHCHILD",
          "FR0010594325",
          "EURONEXT",
          4641,
          "Other",
          0,
          "לא מדורג",
          "אירו",
          405.62,
          14441.0,
          248.75879098056,
          0.001,
          14.09,
          0.38
        ],
        [
          "Fidelity-Italy-Y EUR- FIDELITY FUNDS",
          "LU0318940342",
          "אחר",
          4260,
          "Other",
          0,
          "לא מדורג",
          "אירו",
          6595.05,
          983.1,
          275.34525534054,
          0.001,
          15.6,
          0.42
        ],
        [
          "PICTET-JAPAN EQ- PICTET",
          "LU0895849734",
          "EURONEXT",
          4648,
          "Other",
          0,
          "לא מדורג",
          "דולר אמריקאי",
          2293.28,
          9668.0,
          865.1292391808,
          0.001,
          49.01,
          1.3
        ]
      ]
    },
    "כתבי אופציה": {
      "columns": [
        "שם המנפיק/שם נייר ערך",
        "מספר ני\"ע",
        "זירת מסחר",
        "ענף מסחר",
        "סוג מטבע",
        "ערך נקוב",
        "שער",
        "שווי שוק",
        "שעור מערך נקוב מונפק",
        "שעור מנכסי אפיק ההשקעה",
        "שעור מסך נכסי השקעה"
      ],
      "data": [
        [
          "ארפורט זכויות 2",
          1137132,
          "TASE",
          "נדל\"ן ובינוי",
          "שקל חדש",
          231.25,
          1287,
          2.9761875,
          0.001,
          100,
          0
        ]
      ]
    },
    "לא סחיר- תעודות התחייבות ממשלתי": {
      "columns": [
        "שם המנפיק/שם נייר ערך",
        "מספר ני\"ע",
        "דירוג",
        "שם מדרג",
        "תאריך רכישה",
        "מח\"מ",
        "סוג מטבע",
        "שיעור ריבית",
        "תשואה לפידיון",
        "ערך נקוב",
        "שער",
        "שווי הוגן",
        "שעור מערך נקוב מונפק",
        "שעור מנכסי אפיק ההשקעה",
        "שעור מסך נכסי השקעה"
      ],
      "data": [
        [
          "קופה משותפת 12/15 קרן ט",
          30000178,
          "RF",
          "מעלות",
          "27/12/15",
          0.49,
          "שקל חדש",
          4,
          0.5,
          1000000.0,
          101.750584802621,
          1017.50584802621,
          0.001,
          4.13,
          1.53
        ],
        [
          "אג\"ח ט' מדד 16\\04- האוצר - ממשלתית צמודה",
          39041615,
          "RF",
          "מעלות",
          "26/07/04",
          0.57,
          "שקל חדש",
          4,
          0.5,
          801131.81,
          124.92039514338721,
          1000.77702267137,
          0.001,
          4.07,
          1.51
        ],
        [
          "אג\"ח ט' מדד 17\\05",
          39051713,
          "RF",
          "מעלות",
          "26/07/05",
          1.54,
          "שקל חדש",
          4,
          0.42,
          3669467.8,
          127.30681982710354,
          4671.48276075958,
          0.001,
          18.98,
          7.05
        ],
        [
          "אג\"ח ט' מדד 18\\06- האוצר - ממשלתית צמודה",
          39061811,
          "RF",
          "מעלות",
          "26/07/06",
          2.47,
          "שקל חדש",
          4,
          0.34,
          1407179.67,
          128.71409886796047,
          1811.23863169364,
          0.001,
          7.36,
          2.73
        ],
        [
          "אג\"ח ט' מדד 19\\07",
          39071919,
          "RF",
          "מעלות",
          "11/06/08",
          3.38,
          "שקל חדש",
          4,
          0.14,
          1615061.09,
          133.39721469807003,
          2154.44650973229,
          0.001,
          8.75,
          3.25
        ],
        [
          "אג\"ח ט' מדד 20\\08- האוצר - ממשלתית צמודה",
          39082015,
          "RF",
          "מעלות",
          "25/07/08",
          4.26,
          "שקל חדש",
          4,
          0.12,
          1520714.93,
          131.68084288111712,
          2002.49023764299,
          0.001,
          8.14,
          3.02
        ],
        [
          "אג\"ח ט' מדד 21\\09",
          39092113,
          "RF",
          "מעלות",
          "17/06/10",
          5.11,
          "שקל חדש",
          4,
          0.18,
          3287331.51,
          130.94612208876737,
          4304.63313254712,
          0.001,
          17.49,
          6.49
        ],
        [
          "אג\"ח ט' מדד 22\\10",
          39102219,
          "RF",
          "מעלות",
          "01/07/11",
          5.93,
          "שקל חדש",
          4,
          0.27,
          2153350.64,
          131.94618499711686,
          2841.264019091,
          0.001,
          11.54,
          4.29
        ],
        [
          "אג\"ח ט' מדד 23\\11- האוצר - ממשלתית צמודה",
          39112317,
          "RF",
          "מעלות",
          "26/07/11",
          6.74,
          "שקל חדש",
          4,
          0.36,
          1053078.2,
          130.5385829463719,
          1374.67335959716,
          0.001,
          5.59,
          2.07
        ],
        [
          "אג\"ח ט' מדד 24\\12- האוצר - ממשלתית צמודה",
          39122415,
          "RF",
          "מעלות",
          "23/06/13",
          7.13,
          "שקל חדש",
          4,
          0.41,
          826749.0,
          129.82365378274906,
          1073.31575941234,
          0.001,
          4.36,
          1.62
        ],
        [
          "אג\"ח ט' מדד 25\\13- האוצר - ממשלתית צמודה",
          39132517,
          "RF",
          "מעלות",
          "15/06/14",
          8.28,
          "שקל חדש",
          4,
          0.56,
          1212912.0,
          132.0557287086623,
          1601.71978019481,
          0.001,
          6.51,
          2.42
        ],
        [
          "אג\"ח ט' מדד 26\\14",
          39142617,
          "RF",
          "מעלות",
          "18/06/15",
          9.02,
          "שקל חדש",
          4,
          0.66,
          131255.0,
          134.10358618038094,
          176.017662041059,
          0.001,
          0.72,
          0.27
        ],
        [
          "אג\"ח ט' מדד 27\\15- האוצר - ממשלתית צמודה",
          391527,
          "RF",
          "מעלות",
          "24/07/15",
          9.74,
          "שקל חדש",
          4,
          0.75,
          427861.61,
          136.00330410284508,
          581.905926587629,
          0.001,
          2.36,
          0.88
        ]
      ]
    },
    "לא סחיר - אג\"ח קונצרני": {
      "columns": [
        "שם המנפיק/שם נייר ערך",
        "מספר ני\"ע",
        "ספק המידע",
        "מספר מנפיק",
        "ענף מסחר",
        "דירוג",
        "שם מדרג",
        "תאריך רכישה",
        "מח\"מ",
        "סוג מטבע",
        "שיעור ריבית",
        "תשואה לפידיון",
        "ערך נקוב",
        "שער",
        "שווי הוגן",
        "שעור מערך נקוב מונפק",
        "שעור מנכסי אפיק ההשקעה",
        "שעור מסך נכסי השקעה"
      ],
      "data": [
        [
          "דיבי אס.אגח 2- די.בי.אס שירותי לווין בע\"מ",
          1121490,
          "אחר",
          415,
          "שירותים",
          "AA",
          "מעלות",
          "30/11/14",
          2.26,
          "שקל חדש",
          5.35,
          0.73,
          360727.78,
          117.5,
          423.8551415,
          0.04,
          48.01,
          0.64
        ],
        [
          "בי קומ $144A-רמ- בי קומיוניקיישנס",
          1131226,
          "בלומברג",
          1422,
          "תקשורת ומדיה",
          "A",
          "מעלות",
          "19/02/14",
          4.33,
          "דולר אמריקאי",
          7.38,
          7.0,
          107100.0,
          109.85,
          459.0677637,
          0.01,
          51.99,
          0.69
        ]
      ]
    },
    "לא סחיר - חוזים עתידיים": {
      "columns": [
        "שם המנפיק/שם נייר ערך",
        "מספר ני\"ע",
        "ענף מסחר",
        "סוג מטבע",
        "תאריך רכישה",
        "ערך נקוב",
        "שער",
        "שווי הוגן",
        "שעור מנכסי אפיק ההשקעה",
        "שעור מסך נכסי השקעה"
      ],
      "data": [
        [
          "פורוורד אירו/שקל 4.2605",
          152743,
          "Other",
          "אירו",
          "22/12/15",
          -300000,
          -1.1658509914248067,
          3.49755297427442,
          -290.24,
          0.01
        ],
        [
          "פורוורד דולר/שקל 3.89",
          152742,
          "Other",
          "דולר אמריקאי",
          "22/12/15",
          -960000,
          0.4898555387517396,
          -4.7026131720167,
          390.24,
          -0.01
        ]
      ]
    },
    "הלוואות": {
      "columns": [
        "שם המנפיק/שם נייר ערך",
        "קונסורציום כן/לא",
        "מספר ני\"ע",
        "דירוג",
        "שם מדרג",
        "מח\"מ",
        "סוג מטבע",
        "שיעור ריבית ממוצע",
        "תשואה לפידיון",
        "ערך נקוב",
        "שער",
        "שווי הוגן",
        "שעור מנכסי אפיק ההשקעה",
        "שעור מסך נכסי השקעה",
        "מעלות",
        "שקל חדש"
      ],
      "data": [
        [
          "הלוואות עמיתים",
          "לא",
          1046,
          "AA+",
          "מעלות",
          0.08,
          "שקל חדש",
          5.8,
          1.25,
          201.81,
          94.39884353627868,
          0.190506306140564,
          0.23,
          0.0,
          "",
          ""
        ],
        [
          "הלוואות עמיתים",
          "לא",
          1046,
          "AA+",
          "מעלות",
          0.12,
          "שקל חדש",
          5.8,
          1.31,
          411.64,
          97.99061892377539,
          0.403368583737829,
          0.5,
          0.0,
          "",
          ""
        ],
        [
          "הלוואות עמיתים",
          "לא",
          1046,
          "AA+",
          "מעלות",
          0.17,
          "שקל חדש",
          5.8,
          1.3,
          593.13,
          99.3425211569403,
          0.58923029573816,
          0.72,
          0.0,
          "",
          ""
        ],
        [
          "הלוואות עמיתים",
          "לא",
          1046,
          "AA+",
          "מעלות",
          0.21,
          "שקל חדש",
          5.8,
          1.3,
          755.63,
          99.94019274634027,
          0.755178078449171,
          0.93,
          0.0,
          "",
          ""
        ],
        [
          "הלוואות עמיתים",
          "לא",
          1046,
          "AA+",
          "מעלות",
          0.67,
          "שקל חדש",
          5.8,
          1.31,
          2954.8,
          102.5070215850247,
          3.02887747379431,
          3.72,
          0.0,
          "",
          ""
        ],
        [
          "הלוואות עמיתים",
          "לא",
          1046,
          "AA+",
          "מעלות",
          0.71,
          "שקל חדש",
          5.8,
          1.31,
          2800.67,
          102.44422906793089,
          2.86912479023682,
          3.52,
          0.0,
          "",
          ""
        ],
        [
          "הלוואות עמיתים",
          "לא",
          1046,
          "AA+",
          "מעלות",
          0.75,
          "שקל חדש",
          5.8,
          1.31,
          3019.24,
          102.58051515333594,
          3.09715194571558,
          3.8,
          0.0,
          "",
          ""
        ],
        [
          "הלוואות עמיתים",
          "לא",
          1046,
          "AA+",
          "מעלות",
          0.79,
          "שקל חדש",
          5.8,
          1.31,
          3234.29,
          102.71253266435632,
          3.32202117271001,
          4.08,
          0.01,
          "",
          ""
        ],
        [
          "הלוואות עמיתים",
          "לא",
          1046,
          "AA+",
          "מעלות",
          0.83,
          "שקל חדש",
          5.8,
          1.31,
          3906.98,
          102.6417344261148,
          4.01019203568142,
          4.92,
          0.01,
          "",
          ""
        ],
        [
          "הלוואות עמיתים",
          "לא",
          1046,
          "AA+",
          "מעלות",
          0.87,
          "שקל חדש",
          5.8,
          1.31,
          3450.48,
          102.72853683829584,
          3.54462761789803,
          4.35,
          0.01,
          "",
          ""
        ],
        [
          "הלוואות עמיתים",
          "לא",
          1046,
          "AA+",
          "מעלות",
          0.91,
          "שקל חדש",
          5.8,
          1.31,
          3866.42,
          103.0166383436489,
          3.98305590824651,
          4.89,
          0.01,
          "",
          ""
        ],
        [
          "הלוואות עמיתים",
          "לא",
          1046,
          "AA+",
          "מעלות",
          0.96,
          "שקל חדש",
          5.8,
          1.31,
          4296.78,
          103.50795821216818,
          4.4475092468688,
          5.46,
          0.01,
          "",
          ""
        ],
        [
          "הלוואות עמיתים",
          "לא",
          1046,
          "AA+",
          "מעלות",
          1.0,
          "שקל חדש",
          5.8,
          1.31,
          4153.35,
          103.3925468648255,
          4.29425434521023,
          5.27,
          0.01,
          "",
          ""
        ],
        [
          "הלוואות עמיתים",
          "לא",
          1046,
          "AA+",
          "מעלות",
          1.04,
          "שקל חדש",
          5.8,
          1.31,
          3174.4,
          103.7826935680853,
          3.2944778246253,
          4.04,
          0.0,
          "",
          ""
        ],
        [
          "הלוואות עמיתים",
          "לא",
          1046,
          "AA+",
          "מעלות",
          1.08,
          "שקל חדש",
          5.8,
          1.31,
          3253.97,
          103.97130156282849,
          3.38319496146397,
          4.15,
          0.01,
          "",
          ""
        ],
        [
          "הלוואות עמיתים",
          "לא",
          1046,
          "AA+",
          "מעלות",
          1.12,
          "שקל חדש",
          5.8,
          1.32,
          3798.33,
          105.10265951174121,
          3.99214584703232,
          4.9,
          0.01,
          "",
          ""
        ],
        [
          "הלוואות עמיתים",
          "לא",
          1046,
          "AA+",
          "מעלות",
          1.16,
          "שקל חדש",
          5.8,
          1.32,
          3654.74,
          106.04137620970822,
          3.87553659288669,
          4.76,
          0.01,
          "",
          ""
        ],
        [
          "הלוואות עמיתים",
          "לא",
          1046,
          "AA+",
          "מעלות",
          1.2,
          "שקל חדש",
          5.8,
          1.32,
          2976.79,
          105.91093473408941,
          3.1527461140709,
          3.87,
          0.0,
          "",
          ""
        ],
        [
          "הלוואות עמיתים",
          "לא",
          1046,
          "AA+",
          "מעלות",
          1.24,
          "שקל חדש",
          5.8,
          1.31,
          2575.46,
          105.46494808141847,
          2.7162075518577,
          3.33,
          0.0,
          "",
          ""
        ],
        [
          "הלוואות עמיתים",
          "לא",
          1046,
          "AA+",
          "מעלות",
          1.29,
          "שקל חדש",
          5.8,
          1.31,
          3220.89,
          105.4464833983014,
          3.39631523912755,
          4.17,
          0.01,
          "",
          ""
        ],
        [
          "הלוואות עמיתים",
          "לא",
          1046,
          "AA+",
          "מעלות",
          1.33,
          "שקל חדש",
          5.8,
          1.31,
          2951.0,
          105.32295737686377,
          3.10808047219125,
          3.81,
          0.0,
          "",
          ""
        ],
        [
          "הלוואות עמיתים",
          "לא",
          1046,
          "AA+",
          "מעלות",
          1.37,
          "שקל חדש",
          5.8,
          1.31,
          3139.53,
          105.30854897952241,
          3.3061934877768,
          4.06,
          0.0,
          "",
          ""
        ],
        [
          "הלוואות עמיתים",
          "לא",
          1046,
          "AA+",
          "מעלות",
          1.41,
          "שקל חדש",
          5.8,
          1.3,
          3723.0,
          105.71669905818372,
          3.93583270593618,
          4.83,
          0.01,
          "",
          ""
        ],
        [
          "הלוואות עמיתים",
          "לא",
          1046,
          "AA+",
          "מעלות",
          1.45,
          "שקל חדש",
          5.8,
          1.3,
          4084.93,
          106.34302535093624,
          4.344038145468,
          5.33,
          0.01,
          "",
          ""
        ],
        [
          "הלוואות עמיתים",
          "לא",
          1046,
          "AA+",
          "מעלות",
          1.49,
          "שקל חדש",
          5.8,
          1.29,
          3761.58,
          106.43726646115648,
          4.00372292774957,
          4.91,
          0.01,
          "",
          ""
        ],
        [
          "הלוואות עמיתים",
          "לא",
          1046,
          "AA+",
          "מעלות",
          1.53,
          "שקל חדש",
          5.8,
          1.29,
          4145.0,
          107.06643404002196,
          4.43790369095891,
          5.45,
          0.01,
          "",
          ""
        ]
      ]
    },
    "השקעות אחרות ": {
      "columns": [
        "שם המנפיק/שם נייר ערך",
        "מספר הנייר",
        "דירוג",
        "שם המדרג",
        "שעור הריבית",
        "סוג מטבע",
        "תשואה לפדיון",
        "שווי הוגן",
        "שעור מנכסי אפיק ההשקעה",
        "שעור מסך נכסי השקעה"
      ],
      "data": [
        [
          "SPY - S P 500(דיבידנד לקבל)",
          47373,
          0,
          "לא מדורג",
          0,
          "דולר אמריקאי",
          0,
          2.4964,
          33.04,
          0.0
        ],
        [
          "דלק רכב(דיבידנד לקבל)",
          829010,
          0,
          "לא מדורג",
          0,
          "שקל חדש",
          0,
          1.4266,
          18.88,
          0.0
        ],
        [
          "אשדר      אגח ד(ריבית לקבל)",
          1135607,
          "A3",
          "מידרוג",
          0,
          "שקל חדש",
          0,
          3.633,
          48.08,
          0.01
        ]
      ]
    }
  }
}